{
  "lessons": {
    "Adding": {
      "id": "Adding",
      "title": "Lesson Adding",
      "content": "content/Adding.html",
      "completed": false,
      "unlocked": true,
      "questions": {
        "easy": [
          {
            "id": "Adding_easy_1_fcfb61",
            "content": "A soccer team scored 8 goals in the first half of their game and 10 goals in the second half. How many goals did they score in total?",
            "solution": "18",
            "solution_feedback": "The team scored 8 goals in the first half. They scored 10 goals in the second half. To find the total number of goals, add the goals from both halves: 8 + 10 = 18.",
            "hints": [
              "You need to find the total number of goals.",
              "Add the goals from the first half to the goals from the second half."
            ],
            "correct": false,
            "time_taken": null
          },
          {
            "id": "Adding_easy_2_fcfb61",
            "content": "In a soccer practice, Sarah kicked 10 balls into the net and then kicked 4 more. How many balls did Sarah kick into the net altogether?",
            "solution": "14",
            "solution_feedback": "Sarah kicked 10 balls in the first set. Then she kicked 4 more balls. To find the total, add these two numbers: 10 + 4 = 14.",
            "hints": [
              "Think about combining the two groups of kicks.",
              "Start with the first group of 10 kicks and add the extra 4 kicks to it."
            ],
            "correct": false,
            "time_taken": null
          },
          {
            "id": "Adding_easy_3_fcfb61",
            "content": "A striker made 9 goals in one game and 8 goals in the next game. What is the total number of goals the striker scored in both games?",
            "solution": "17",
            "solution_feedback": "The striker scored 9 goals in the first game and 8 goals in the second game. To find the total, add the goals from both games: 9 + 8 = 17.",
            "hints": [
              "You are looking for a total.",
              "Combine the goals from the first game with the goals from the second game."
            ],
            "correct": false,
            "time_taken": null
          }
        ],
        "medium": [
          {
            "id": "Adding_medium_1_fcfb61",
            "content": "3 + 41 =",
            "solution": "44",
            "solution_feedback": null,
            "hints": [
              "Try breaking the problem into smaller steps."
            ],
            "correct": false,
            "time_taken": null
          },
          {
            "id": "Adding_medium_2_fcfb61",
            "content": "A soccer team won 44 games in their first season and 8 games in their second season. How many games did they win in total over the two seasons?",
            "solution": "52",
            "solution_feedback": "The team won 44 games in the first season and 8 games in the second season. To find the total games won, add these numbers: 44 + 8 = 52.",
            "hints": [
              "You need to find the sum of games won.",
              "Add the number of games won in the first season to the number of games won in the second season."
            ],
            "correct": false,
            "time_taken": null
          },
          {
            "id": "Adding_medium_3_fcfb61",
            "content": "During a soccer tournament, one player scored 1 goal in the first match and 10 goals in the second match. How many goals did the player score in total?",
            "solution": "11",
            "solution_feedback": "The player scored 1 goal in the first match and 10 goals in the second match. To find the total number of goals, add these two amounts: 1 + 10 = 11.",
            "hints": [
              "Combine the goals from both matches.",
              "Add the goals scored in the first match to the goals scored in the second match."
            ],
            "correct": false,
            "time_taken": null
          }
        ],
        "hard": [
          {
            "id": "Adding_hard_1_fcfb61",
            "content": "A soccer team played three matches. They scored 41 goals in the first match, 8 goals in the second match, and 8 goals in the third match. How many goals did they score in total across all three matches?",
            "solution": "57",
            "solution_feedback": "The team scored 41 goals in the first match, 8 in the second, and 8 in the third. To find the total, add all these numbers: 41 + 8 + 8 = 57.",
            "hints": [
              "You need to find the sum of all goals.",
              "Add the goals from the first match, the second match, and the third match together."
            ],
            "correct": false,
            "time_taken": null
          },
          {
            "id": "Adding_hard_2_fcfb61",
            "content": "In a soccer season, a player scored 14 goals in the first half of the season and then scored 9 goals in the second half and another 9 goals in the playoffs. How many goals did the player score in total?",
            "solution": "32",
            "solution_feedback": "The player scored 14 goals in the first half, 9 in the second half, and 9 in the playoffs. To find the total, add these numbers: 14 + 9 + 9 = 32.",
            "hints": [
              "Add all the goals scored over the season and playoffs.",
              "First, add the goals from the first half and the second half. Then, add the goals from the playoffs to that sum."
            ],
            "correct": false,
            "time_taken": null
          },
          {
            "id": "Adding_hard_3_fcfb61",
            "content": "A soccer team scored 19 goals in their first game, 3 goals in their second game, and 2 goals in their third game. What is the total number of goals scored by the team in these three games?",
            "solution": "24",
            "solution_feedback": "The team scored 19 goals in the first game, 3 goals in the second game, and 2 goals in the third game. To find the total, add these amounts: 19 + 3 + 2 = 24.",
            "hints": [
              "Combine the goals from all three games.",
              "Add the goals from the first game, the second game, and the third game."
            ],
            "correct": false,
            "time_taken": null
          }
        ]
      }
    },
    "Subtracting": {
      "id": "Subtracting",
      "title": "Lesson Subtracting",
      "content": "content/Subtracting.html",
      "completed": false,
      "unlocked": false,
      "questions": {
        "easy": [
          {
            "id": "Subtracting_easy_1_fcfb61",
            "content": "9 - 6 =",
            "solution": "3",
            "solution_feedback": null,
            "hints": [
              "Try breaking the problem into smaller steps."
            ],
            "correct": false,
            "time_taken": null
          },
          {
            "id": "Subtracting_easy_2_fcfb61",
            "content": "7 - 4 =",
            "solution": "3",
            "solution_feedback": null,
            "hints": [
              "Try breaking the problem into smaller steps."
            ],
            "correct": false,
            "time_taken": null
          },
          {
            "id": "Subtracting_easy_3_fcfb61",
            "content": "9 - 6 =",
            "solution": "3",
            "solution_feedback": null,
            "hints": [
              "Try breaking the problem into smaller steps."
            ],
            "correct": false,
            "time_taken": null
          }
        ],
        "medium": [
          {
            "id": "Subtracting_medium_1_fcfb61",
            "content": "36 - 3 =",
            "solution": "33",
            "solution_feedback": null,
            "hints": [
              "Try breaking the problem into smaller steps."
            ],
            "correct": false,
            "time_taken": null
          },
          {
            "id": "Subtracting_medium_2_fcfb61",
            "content": "45 - 12 =",
            "solution": "33",
            "solution_feedback": null,
            "hints": [
              "Try breaking the problem into smaller steps."
            ],
            "correct": false,
            "time_taken": null
          },
          {
            "id": "Subtracting_medium_3_fcfb61",
            "content": "39 - 37 =",
            "solution": "2",
            "solution_feedback": null,
            "hints": [
              "Try breaking the problem into smaller steps."
            ],
            "correct": false,
            "time_taken": null
          }
        ],
        "hard": [
          {
            "id": "Subtracting_hard_1_fcfb61",
            "content": "31 - 6 - 11 =",
            "solution": "14",
            "solution_feedback": null,
            "hints": [
              "Try breaking the problem into smaller steps."
            ],
            "correct": false,
            "time_taken": null
          },
          {
            "id": "Subtracting_hard_2_fcfb61",
            "content": "49 - 21 =",
            "solution": "28",
            "solution_feedback": null,
            "hints": [
              "Try breaking the problem into smaller steps."
            ],
            "correct": false,
            "time_taken": null
          },
          {
            "id": "Subtracting_hard_3_fcfb61",
            "content": "33 - 28 - 1 =",
            "solution": "4",
            "solution_feedback": null,
            "hints": [
              "Try breaking the problem into smaller steps."
            ],
            "correct": false,
            "time_taken": null
          }
        ]
      }
    },
    "Review Adding Subtracting": {
      "id": "Review Adding Subtracting",
      "title": "Lesson Review Adding Subtracting",
      "content": "content/Review Adding Subtracting.html",
      "completed": false,
      "unlocked": false,
      "questions": {
        "easy": [
          {
            "id": "Review Adding Subtracting_easy_1_fcfb61",
            "content": "5 - 1 =",
            "solution": "4",
            "solution_feedback": null,
            "hints": [
              "Try breaking the problem into smaller steps."
            ],
            "correct": false,
            "time_taken": null
          },
          {
            "id": "Review Adding Subtracting_easy_2_fcfb61",
            "content": "2 + 5 =",
            "solution": "7",
            "solution_feedback": null,
            "hints": [
              "Try breaking the problem into smaller steps."
            ],
            "correct": false,
            "time_taken": null
          },
          {
            "id": "Review Adding Subtracting_easy_3_fcfb61",
            "content": "1 + 8 =",
            "solution": "9",
            "solution_feedback": null,
            "hints": [
              "Try breaking the problem into smaller steps."
            ],
            "correct": false,
            "time_taken": null
          }
        ],
        "medium": [
          {
            "id": "Review Adding Subtracting_medium_1_fcfb61",
            "content": "10 - 10 =",
            "solution": "0",
            "solution_feedback": null,
            "hints": [
              "Try breaking the problem into smaller steps."
            ],
            "correct": false,
            "time_taken": null
          },
          {
            "id": "Review Adding Subtracting_medium_2_fcfb61",
            "content": "29 + 2 =",
            "solution": "31",
            "solution_feedback": null,
            "hints": [
              "Try breaking the problem into smaller steps."
            ],
            "correct": false,
            "time_taken": null
          },
          {
            "id": "Review Adding Subtracting_medium_3_fcfb61",
            "content": "40 - 1 =",
            "solution": "39",
            "solution_feedback": null,
            "hints": [
              "Try breaking the problem into smaller steps."
            ],
            "correct": false,
            "time_taken": null
          }
        ],
        "hard": [
          {
            "id": "Review Adding Subtracting_hard_1_fcfb61",
            "content": "18 - 10 =",
            "solution": "8",
            "solution_feedback": null,
            "hints": [
              "Try breaking the problem into smaller steps."
            ],
            "correct": false,
            "time_taken": null
          },
          {
            "id": "Review Adding Subtracting_hard_2_fcfb61",
            "content": "19 + 9 + 6 =",
            "solution": "34",
            "solution_feedback": null,
            "hints": [
              "Try breaking the problem into smaller steps."
            ],
            "correct": false,
            "time_taken": null
          },
          {
            "id": "Review Adding Subtracting_hard_3_fcfb61",
            "content": "31 + 6 + 6 =",
            "solution": "43",
            "solution_feedback": null,
            "hints": [
              "Try breaking the problem into smaller steps."
            ],
            "correct": false,
            "time_taken": null
          }
        ]
      }
    },
    "Adding With Blanks": {
      "id": "Adding With Blanks",
      "title": "Lesson Adding With Blanks",
      "content": "content/Adding With Blanks.html",
      "completed": false,
      "unlocked": false,
      "questions": {
        "easy": [
          {
            "id": "Adding With Blanks_easy_1_fcfb61",
            "content": "3 + _ = 8",
            "solution": "5",
            "solution_feedback": null,
            "hints": [
              "Try breaking the problem into smaller steps."
            ],
            "correct": false,
            "time_taken": null
          },
          {
            "id": "Adding With Blanks_easy_2_fcfb61",
            "content": "_ + 3 = 8",
            "solution": "5",
            "solution_feedback": null,
            "hints": [
              "Try breaking the problem into smaller steps."
            ],
            "correct": false,
            "time_taken": null
          },
          {
            "id": "Adding With Blanks_easy_3_fcfb61",
            "content": "_ + 1 = 8",
            "solution": "7",
            "solution_feedback": null,
            "hints": [
              "Try breaking the problem into smaller steps."
            ],
            "correct": false,
            "time_taken": null
          }
        ],
        "medium": [
          {
            "id": "Adding With Blanks_medium_1_fcfb61",
            "content": "6 + _ = 7",
            "solution": "1",
            "solution_feedback": null,
            "hints": [
              "Try breaking the problem into smaller steps."
            ],
            "correct": false,
            "time_taken": null
          },
          {
            "id": "Adding With Blanks_medium_2_fcfb61",
            "content": "1 + _ = 2",
            "solution": "1",
            "solution_feedback": null,
            "hints": [
              "Try breaking the problem into smaller steps."
            ],
            "correct": false,
            "time_taken": null
          },
          {
            "id": "Adding With Blanks_medium_3_fcfb61",
            "content": "_ + 2 = 8",
            "solution": "6",
            "solution_feedback": null,
            "hints": [
              "Try breaking the problem into smaller steps."
            ],
            "correct": false,
            "time_taken": null
          }
        ],
        "hard": [
          {
            "id": "Adding With Blanks_hard_1_fcfb61",
            "content": "__ + 34 = 39",
            "solution": "5",
            "solution_feedback": null,
            "hints": [
              "Try breaking the problem into smaller steps."
            ],
            "correct": false,
            "time_taken": null
          },
          {
            "id": "Adding With Blanks_hard_2_fcfb61",
            "content": "__ + 21 = 45",
            "solution": "24",
            "solution_feedback": null,
            "hints": [
              "Try breaking the problem into smaller steps."
            ],
            "correct": false,
            "time_taken": null
          },
          {
            "id": "Adding With Blanks_hard_3_fcfb61",
            "content": "__ + 17 = 24",
            "solution": "7",
            "solution_feedback": null,
            "hints": [
              "Try breaking the problem into smaller steps."
            ],
            "correct": false,
            "time_taken": null
          }
        ]
      }
    },
    "Subtracting With Blanks": {
      "id": "Subtracting With Blanks",
      "title": "Lesson Subtracting With Blanks",
      "content": "content/Subtracting With Blanks.html",
      "completed": false,
      "unlocked": false,
      "questions": {
        "easy": [
          {
            "id": "Subtracting With Blanks_easy_1_fcfb61",
            "content": "6 - _ = 4",
            "solution": "2",
            "solution_feedback": null,
            "hints": [
              "Try breaking the problem into smaller steps."
            ],
            "correct": false,
            "time_taken": null
          },
          {
            "id": "Subtracting With Blanks_easy_2_fcfb61",
            "content": "3 - _ = 2",
            "solution": "1",
            "solution_feedback": null,
            "hints": [
              "Try breaking the problem into smaller steps."
            ],
            "correct": false,
            "time_taken": null
          },
          {
            "id": "Subtracting With Blanks_easy_3_fcfb61",
            "content": "_ - 5 = 0",
            "solution": "5",
            "solution_feedback": null,
            "hints": [
              "Try breaking the problem into smaller steps."
            ],
            "correct": false,
            "time_taken": null
          }
        ],
        "medium": [
          {
            "id": "Subtracting With Blanks_medium_1_fcfb61",
            "content": "_ - 9 = 7",
            "solution": "16",
            "solution_feedback": null,
            "hints": [
              "Try breaking the problem into smaller steps."
            ],
            "correct": false,
            "time_taken": null
          },
          {
            "id": "Subtracting With Blanks_medium_2_fcfb61",
            "content": "_ - 4 = 16",
            "solution": "20",
            "solution_feedback": null,
            "hints": [
              "Try breaking the problem into smaller steps."
            ],
            "correct": false,
            "time_taken": null
          },
          {
            "id": "Subtracting With Blanks_medium_3_fcfb61",
            "content": "23 - _ = 22",
            "solution": "1",
            "solution_feedback": null,
            "hints": [
              "Try breaking the problem into smaller steps."
            ],
            "correct": false,
            "time_taken": null
          }
        ],
        "hard": [
          {
            "id": "Subtracting With Blanks_hard_1_fcfb61",
            "content": "_ - 12 = 21",
            "solution": "33",
            "solution_feedback": null,
            "hints": [
              "Try breaking the problem into smaller steps."
            ],
            "correct": false,
            "time_taken": null
          },
          {
            "id": "Subtracting With Blanks_hard_2_fcfb61",
            "content": "_ - 22 = 25",
            "solution": "47",
            "solution_feedback": null,
            "hints": [
              "Try breaking the problem into smaller steps."
            ],
            "correct": false,
            "time_taken": null
          },
          {
            "id": "Subtracting With Blanks_hard_3_fcfb61",
            "content": "_ - 13 = 8",
            "solution": "21",
            "solution_feedback": null,
            "hints": [
              "Try breaking the problem into smaller steps."
            ],
            "correct": false,
            "time_taken": null
          }
        ]
      }
    },
    "Review Adding Subtracting With Blanks": {
      "id": "Review Adding Subtracting With Blanks",
      "title": "Lesson Review Adding Subtracting With Blanks",
      "content": "content/Review Adding Subtracting With Blanks.html",
      "completed": false,
      "unlocked": false,
      "questions": {
        "easy": [
          {
            "id": "Review Adding Subtracting With Blanks_easy_1_fcfb61",
            "content": "5 + _ = 9",
            "solution": "4",
            "solution_feedback": null,
            "hints": [
              "Try breaking the problem into smaller steps."
            ],
            "correct": false,
            "time_taken": null
          },
          {
            "id": "Review Adding Subtracting With Blanks_easy_2_fcfb61",
            "content": "2 + _ = 2",
            "solution": "0",
            "solution_feedback": null,
            "hints": [
              "Try breaking the problem into smaller steps."
            ],
            "correct": false,
            "time_taken": null
          },
          {
            "id": "Review Adding Subtracting With Blanks_easy_3_fcfb61",
            "content": "_ - 1 = 6",
            "solution": "7",
            "solution_feedback": null,
            "hints": [
              "Try breaking the problem into smaller steps."
            ],
            "correct": false,
            "time_taken": null
          }
        ],
        "medium": [
          {
            "id": "Review Adding Subtracting With Blanks_medium_1_fcfb61",
            "content": "_ + 9 = 16",
            "solution": "7",
            "solution_feedback": null,
            "hints": [
              "Try breaking the problem into smaller steps."
            ],
            "correct": false,
            "time_taken": null
          },
          {
            "id": "Review Adding Subtracting With Blanks_medium_2_fcfb61",
            "content": "1 + _ = 10",
            "solution": "9",
            "solution_feedback": null,
            "hints": [
              "Try breaking the problem into smaller steps."
            ],
            "correct": false,
            "time_taken": null
          },
          {
            "id": "Review Adding Subtracting With Blanks_medium_3_fcfb61",
            "content": "22 - _ = 18",
            "solution": "4",
            "solution_feedback": null,
            "hints": [
              "Try breaking the problem into smaller steps."
            ],
            "correct": false,
            "time_taken": null
          }
        ],
        "hard": [
          {
            "id": "Review Adding Subtracting With Blanks_hard_1_fcfb61",
            "content": "10 - _ = 4",
            "solution": "6",
            "solution_feedback": null,
            "hints": [
              "Try breaking the problem into smaller steps."
            ],
            "correct": false,
            "time_taken": null
          },
          {
            "id": "Review Adding Subtracting With Blanks_hard_2_fcfb61",
            "content": "__ + 14 = 22",
            "solution": "8",
            "solution_feedback": null,
            "hints": [
              "Try breaking the problem into smaller steps."
            ],
            "correct": false,
            "time_taken": null
          },
          {
            "id": "Review Adding Subtracting With Blanks_hard_3_fcfb61",
            "content": "_ - 2 = 48",
            "solution": "50",
            "solution_feedback": null,
            "hints": [
              "Try breaking the problem into smaller steps."
            ],
            "correct": false,
            "time_taken": null
          }
        ]
      }
    },
    "Adding With N Amount": {
      "id": "Adding With N Amount",
      "title": "Lesson Adding With N Amount",
      "content": "content/Adding With N Amount.html",
      "completed": false,
      "unlocked": false,
      "questions": {
        "easy": [
          {
            "id": "Adding With N Amount_easy_1_fcfb61",
            "content": "0 + __ + 7 = 13",
            "solution": "6",
            "solution_feedback": null,
            "hints": [
              "Try breaking the problem into smaller steps."
            ],
            "correct": false,
            "time_taken": null
          },
          {
            "id": "Adding With N Amount_easy_2_fcfb61",
            "content": "__ + 7 + 3 = 20",
            "solution": "10",
            "solution_feedback": null,
            "hints": [
              "Try breaking the problem into smaller steps."
            ],
            "correct": false,
            "time_taken": null
          },
          {
            "id": "Adding With N Amount_easy_3_fcfb61",
            "content": "__ + 5 + 0 = 8",
            "solution": "3",
            "solution_feedback": null,
            "hints": [
              "Try breaking the problem into smaller steps."
            ],
            "correct": false,
            "time_taken": null
          }
        ],
        "medium": [
          {
            "id": "Adding With N Amount_medium_1_fcfb61",
            "content": "7 + 10 + __ + 11 = 41",
            "solution": "13",
            "solution_feedback": null,
            "hints": [
              "Try breaking the problem into smaller steps."
            ],
            "correct": false,
            "time_taken": null
          },
          {
            "id": "Adding With N Amount_medium_2_fcfb61",
            "content": "14 + __ + 24 + 17 = 70",
            "solution": "15",
            "solution_feedback": null,
            "hints": [
              "Try breaking the problem into smaller steps."
            ],
            "correct": false,
            "time_taken": null
          },
          {
            "id": "Adding With N Amount_medium_3_fcfb61",
            "content": "6 + 23 + 4 + __ = 36",
            "solution": "3",
            "solution_feedback": null,
            "hints": [
              "Try breaking the problem into smaller steps."
            ],
            "correct": false,
            "time_taken": null
          }
        ],
        "hard": [
          {
            "id": "Adding With N Amount_hard_1_fcfb61",
            "content": "__ + 17 + 47 + 35 = 138",
            "solution": "39",
            "solution_feedback": null,
            "hints": [
              "Try breaking the problem into smaller steps."
            ],
            "correct": false,
            "time_taken": null
          },
          {
            "id": "Adding With N Amount_hard_2_fcfb61",
            "content": "19 + 41 + __ + 6 = 83",
            "solution": "17",
            "solution_feedback": null,
            "hints": [
              "Try breaking the problem into smaller steps."
            ],
            "correct": false,
            "time_taken": null
          },
          {
            "id": "Adding With N Amount_hard_3_fcfb61",
            "content": "__ + 25 + 8 + 33 = 73",
            "solution": "7",
            "solution_feedback": null,
            "hints": [
              "Try breaking the problem into smaller steps."
            ],
            "correct": false,
            "time_taken": null
          }
        ]
      }
    },
    "Subtracting With N Amount": {
      "id": "Subtracting With N Amount",
      "title": "Lesson Subtracting With N Amount",
      "content": "content/Subtracting With N Amount.html",
      "completed": false,
      "unlocked": false,
      "questions": {
        "easy": [
          {
            "id": "Subtracting With N Amount_easy_1_fcfb61",
            "content": "7 - 6 - __ = -1",
            "solution": "2",
            "solution_feedback": null,
            "hints": [
              "Try breaking the problem into smaller steps."
            ],
            "correct": false,
            "time_taken": null
          },
          {
            "id": "Subtracting With N Amount_easy_2_fcfb61",
            "content": "8 - 4 - __ = 0",
            "solution": "4",
            "solution_feedback": null,
            "hints": [
              "Try breaking the problem into smaller steps."
            ],
            "correct": false,
            "time_taken": null
          },
          {
            "id": "Subtracting With N Amount_easy_3_fcfb61",
            "content": "__ - 4 - 2 = -1",
            "solution": "5",
            "solution_feedback": null,
            "hints": [
              "Try breaking the problem into smaller steps."
            ],
            "correct": false,
            "time_taken": null
          }
        ],
        "medium": [
          {
            "id": "Subtracting With N Amount_medium_1_fcfb61",
            "content": "__ - 18 - 12 - 9 = -17",
            "solution": "22",
            "solution_feedback": null,
            "hints": [
              "Try breaking the problem into smaller steps."
            ],
            "correct": false,
            "time_taken": null
          },
          {
            "id": "Subtracting With N Amount_medium_2_fcfb61",
            "content": "__ - 23 - 19 - 16 = -35",
            "solution": "23",
            "solution_feedback": null,
            "hints": [
              "Try breaking the problem into smaller steps."
            ],
            "correct": false,
            "time_taken": null
          },
          {
            "id": "Subtracting With N Amount_medium_3_fcfb61",
            "content": "12 - 12 - 10 - __ = -15",
            "solution": "5",
            "solution_feedback": null,
            "hints": [
              "Try breaking the problem into smaller steps."
            ],
            "correct": false,
            "time_taken": null
          }
        ],
        "hard": [
          {
            "id": "Subtracting With N Amount_hard_1_fcfb61",
            "content": "41 - __ - 16 - 12 = -11",
            "solution": "24",
            "solution_feedback": null,
            "hints": [
              "Try breaking the problem into smaller steps."
            ],
            "correct": false,
            "time_taken": null
          },
          {
            "id": "Subtracting With N Amount_hard_2_fcfb61",
            "content": "49 - __ - 42 - 27 = -65",
            "solution": "45",
            "solution_feedback": null,
            "hints": [
              "Try breaking the problem into smaller steps."
            ],
            "correct": false,
            "time_taken": null
          },
          {
            "id": "Subtracting With N Amount_hard_3_fcfb61",
            "content": "27 - 18 - 16 - __ = -9",
            "solution": "2",
            "solution_feedback": null,
            "hints": [
              "Try breaking the problem into smaller steps."
            ],
            "correct": false,
            "time_taken": null
          }
        ]
      }
    },
    "Adding Subtracting With N Amount Review": {
      "id": "Adding Subtracting With N Amount Review",
      "title": "Lesson Adding Subtracting With N Amount Review",
      "content": "content/Adding Subtracting With N Amount Review.html",
      "completed": false,
      "unlocked": false,
      "questions": {
        "easy": [
          {
            "id": "Adding Subtracting With N Amount Review_easy_1_fcfb61",
            "content": "6 + __ + 10 = 19",
            "solution": "3",
            "solution_feedback": null,
            "hints": [
              "Try breaking the problem into smaller steps."
            ],
            "correct": false,
            "time_taken": null
          },
          {
            "id": "Adding Subtracting With N Amount Review_easy_2_fcfb61",
            "content": "4 + __ + 10 = 17",
            "solution": "3",
            "solution_feedback": null,
            "hints": [
              "Try breaking the problem into smaller steps."
            ],
            "correct": false,
            "time_taken": null
          },
          {
            "id": "Adding Subtracting With N Amount Review_easy_3_fcfb61",
            "content": "10 - 5 - __ = 1",
            "solution": "4",
            "solution_feedback": null,
            "hints": [
              "Try breaking the problem into smaller steps."
            ],
            "correct": false,
            "time_taken": null
          }
        ],
        "medium": [
          {
            "id": "Adding Subtracting With N Amount Review_medium_1_fcfb61",
            "content": "25 - __ - 5 - 5 = 9",
            "solution": "6",
            "solution_feedback": null,
            "hints": [
              "Try breaking the problem into smaller steps."
            ],
            "correct": false,
            "time_taken": null
          },
          {
            "id": "Adding Subtracting With N Amount Review_medium_2_fcfb61",
            "content": "__ + 6 + 4 + 17 = 45",
            "solution": "18",
            "solution_feedback": null,
            "hints": [
              "Try breaking the problem into smaller steps."
            ],
            "correct": false,
            "time_taken": null
          },
          {
            "id": "Adding Subtracting With N Amount Review_medium_3_fcfb61",
            "content": "18 + __ + 13 + 24 = 67",
            "solution": "12",
            "solution_feedback": null,
            "hints": [
              "Try breaking the problem into smaller steps."
            ],
            "correct": false,
            "time_taken": null
          }
        ],
        "hard": [
          {
            "id": "Adding Subtracting With N Amount Review_hard_1_fcfb61",
            "content": "46 + 18 + __ + 42 = 147",
            "solution": "41",
            "solution_feedback": null,
            "hints": [
              "Try breaking the problem into smaller steps."
            ],
            "correct": false,
            "time_taken": null
          },
          {
            "id": "Adding Subtracting With N Amount Review_hard_2_fcfb61",
            "content": "40 - 22 - 7 - __ = 9",
            "solution": "2",
            "solution_feedback": null,
            "hints": [
              "Try breaking the problem into smaller steps."
            ],
            "correct": false,
            "time_taken": null
          },
          {
            "id": "Adding Subtracting With N Amount Review_hard_3_fcfb61",
            "content": "27 + 29 + __ + 11 = 114",
            "solution": "47",
            "solution_feedback": null,
            "hints": [
              "Try breaking the problem into smaller steps."
            ],
            "correct": false,
            "time_taken": null
          }
        ]
      }
    }
  }
}